MANIFEST.in
README.md
setup.py
jk_new_lib.egg-info/PKG-INFO
jk_new_lib.egg-info/SOURCES.txt
jk_new_lib.egg-info/dependency_links.txt
jk_new_lib.egg-info/top_level.txt
package/__init__.py
package/factorial.py