Metadata-Version: 1.0
Name: jk-new-lib
Version: 1.0.0
Summary: Super useful library
Home-page: UNKNOWN
Author: kalisz
Author-email: kalisz90@vp.pl
License: UNKNOWN
Platform: UNKNOWN
